mcp_ip/__init__.py
mcp_ip/main.py
mcp_ip-0.1.6.dist-info/METADATA
mcp_ip-0.1.6.dist-info/WHEEL
mcp_ip-0.1.6.dist-info/entry_points.txt
mcp_ip-0.1.6.dist-info/RECORD
