Metadata-Version: 2.4
Name: mcp-ip
Version: 0.1.6
Summary: Add your description here
Requires-Python: >=3.11
Requires-Dist: fastapi>=0.115.12
Requires-Dist: mcp>=1.6.0
Requires-Dist: uvicorn>=0.34.2
